TDLM/__init__.py
TDLM/tdlm.py
pytdlm-0.1.0.dist-info/licenses/LICENSE
pytdlm-0.1.0.dist-info/METADATA
pytdlm-0.1.0.dist-info/WHEEL
pytdlm-0.1.0.dist-info/top_level.txt
pytdlm-0.1.0.dist-info/RECORD
