Metadata-Version: 2.4
Name: PyTDLM
Version: 0.1.0
Summary: Systematic comparison of trip distribution laws and models
Author-email: Maxime Lenormand <maxime.lenormand@inrae.fr>
License: GPL-3.0
Project-URL: Homepage, https://github.com/RTDLM/PyTDLM
Project-URL: Repository, https://github.com/RTDLM/PyTDLM
Project-URL: Documentation, https://rtdlm.github.io/PyTDLM/
Project-URL: Bug Tracker, https://github.com/RTDLM/PyTDLM/issues
Keywords: spatial-interaction,gravity-model,trip-distribution
Classifier: Development Status :: 4 - Beta
Classifier: Intended Audience :: Science/Research
Classifier: License :: OSI Approved :: GNU General Public License v3 (GPLv3)
Classifier: Programming Language :: Python :: 3
Classifier: Programming Language :: Python :: 3.8
Classifier: Programming Language :: Python :: 3.9
Classifier: Programming Language :: Python :: 3.10
Classifier: Programming Language :: Python :: 3.11
Classifier: Programming Language :: Python :: 3.12
Classifier: Programming Language :: Python :: 3.13
Requires-Python: >=3.8
License-File: LICENSE
Requires-Dist: numpy>=1.20.0
Requires-Dist: pandas>=1.3.0
Requires-Dist: tabulate>=0.9.0
Requires-Dist: tqdm>=4.60.0
Provides-Extra: dev
Requires-Dist: pytest>=6.0; extra == "dev"
Requires-Dist: pytest-cov>=2.0; extra == "dev"
Requires-Dist: black>=22.0; extra == "dev"
Requires-Dist: flake8>=4.0; extra == "dev"
Requires-Dist: isort>=5.0; extra == "dev"
Provides-Extra: docs
Requires-Dist: sphinx>=4.0; extra == "docs"
Requires-Dist: sphinx-rtd-theme>=1.0; extra == "docs"
Dynamic: license-file
